setup.py
dagilimlar/Binomialdistribution.py
dagilimlar/Gaussiandistribution.py
dagilimlar/Generaldistribution.py
dagilimlar/__init__.py
dagilimlar.egg-info/PKG-INFO
dagilimlar.egg-info/SOURCES.txt
dagilimlar.egg-info/dependency_links.txt
dagilimlar.egg-info/not-zip-safe
dagilimlar.egg-info/top_level.txt